{   
    "base_graphs": {
        "grid_dims" : [5,5],
        "playground_size": [120, 120],
        "max_room_entry_size" : 4,
        "room_center_distances" : [5,5],
        "wall_thickness" : 0.5,
        "n_buildings" : 1
    },
    "noise":{
        "global":{
            "active": true,
            "translation": 1,
            "rotation": 0
        },
        "room": {
            "active": false,
            "translation": 0.05,
            "rotation": 0.002
        },
        "ws": {
            "active": false,
            "rotation": 0.005
        }
    },
    "multiview": {
        "number":2,
        "overlapping": 4
    },
    "training_split": {
        "val" : 0.0,
        "test" : 0.0
    },
    "postprocess": {
        "training": {
            "use_gt": true,
            "K_nearest": 0,
            "K_random" : 0
        },
        "final": {
            "use_gt": false,
            "K_nearest": 8,
            "K_random" : 0
        }
    }
}